{
	"format_version": "1.12.0",
	"minecraft:geometry": [
		{
			"description": {
				"identifier": "geometry.petshop",
				"texture_width": 32,
				"texture_height": 32,
				"visible_bounds_width": 2,
				"visible_bounds_height": 2.5,
				"visible_bounds_offset": [0, 0.75, 0]
			},
			"bones": [
				{
					"name": "torso",
					"pivot": [0, 6.325, -1],
					"rotation": [90, -67.5, -90]
				},
				{
					"name": "body",
					"parent": "torso",
					"pivot": [0.15851, 4.09456, -1],
					"rotation": [0, 0, 15],
					"cubes": [
						{"origin": [-1.67981, 3.65357, -3], "size": [3, 4.9, 4], "uv": [0, 0]}
					]
				},
				{
					"name": "tail",
					"parent": "body",
					"pivot": [1.07612, 3.70768, -1],
					"cubes": [
						{"origin": [0.32019, -0.34643, -3], "size": [1, 4, 4], "uv": [12, 5]}
					]
				},
				{
					"name": "head",
					"parent": "body",
					"pivot": [-0.42388, 8.95768, -1],
					"cubes": [
						{"origin": [-1.75129, 9.15357, -2.67259], "size": [3, 3, 3], "pivot": [-0.42388, 10.70768, -1], "rotation": [0, -45, 0], "uv": [13, 13]},
						{"origin": [-2.67981, 9.15357, -1.5], "size": [1, 1, 1], "uv": [22, 9]},
						{
							"origin": [-2.95129, 9.15357, -1.17259],
							"size": [0.7, 0.9, 0.7],
							"pivot": [-2.42388, 9.70768, -1],
							"rotation": [0, -45, 0],
							"uv": {
								"north": {"uv": [22, 11], "uv_size": [1, 1]},
								"east": {"uv": [25, 11], "uv_size": [1, 1]},
								"south": {"uv": [23, 11], "uv_size": [1, 1]},
								"west": {"uv": [24, 11], "uv_size": [1, 1]},
								"up": {"uv": [24, 13], "uv_size": [-1, -1]},
								"down": {"uv": [25, 13], "uv_size": [-1, -1]}
							}
						}
					]
				},
				{
					"name": "eyes2",
					"parent": "head",
					"pivot": [-1.82388, 10.55768, -0.25],
					"rotation": [0, 45, 0],
					"cubes": [
						{
							"origin": [-1.65129, 10.25357, -0.32741],
							"size": [0, 0.5, 1],
							"uv": {
								"north": {"uv": [17, 26], "uv_size": [-1, 1]},
								"east": {"uv": [16, 26], "uv_size": [-2, 1]},
								"south": {"uv": [16, 26], "uv_size": [-1, 1]},
								"west": {"uv": [17, 26], "uv_size": [-2, 1]},
								"up": {"uv": [16, 27], "uv_size": [-1, -2]},
								"down": {"uv": [16, 25], "uv_size": [-1, 2]}
							}
						}
					]
				},
				{
					"name": "eyelid2",
					"parent": "eyes2",
					"pivot": [-1.82388, 10.95768, -0.25],
					"cubes": [
						{
							"origin": [-1.75129, 10.61075, -0.5473],
							"size": [0.2, 0.4, 1.275],
							"pivot": [-1.92388, 10.95768, 0],
							"rotation": [15, 0, 0],
							"uv": {
								"north": {"uv": [17, 27], "uv_size": [-1, 1]},
								"east": {"uv": [16, 27], "uv_size": [-2, 1]},
								"south": {"uv": [16, 27], "uv_size": [-1, 1]},
								"west": {"uv": [17, 26], "uv_size": [-2, 1]},
								"up": {"uv": [16, 29], "uv_size": [-1, -2]},
								"down": {"uv": [16, 25], "uv_size": [-1, 2]}
							}
						}
					]
				},
				{
					"name": "iris2",
					"parent": "eyes2",
					"pivot": [-1.92388, 10.55768, -0.25],
					"cubes": [
						{
							"origin": [-1.70129, 10.25357, -0.42741],
							"size": [0, 0.5, 0.5],
							"uv": {
								"north": {"uv": [3, 2], "uv_size": [-1, 1]},
								"east": {"uv": [18, 26], "uv_size": [-1, 1]},
								"south": {"uv": [3, 2], "uv_size": [-1, 1]},
								"west": {"uv": [3, 2], "uv_size": [-1, 1]},
								"up": {"uv": [3, 2], "uv_size": [-1, 1]},
								"down": {"uv": [3, 2], "uv_size": [-1, 1]}
							}
						}
					]
				},
				{
					"name": "eyes",
					"parent": "head",
					"pivot": [-1.82388, 10.55768, -1.75],
					"rotation": [0, -45, 0],
					"cubes": [
						{
							"origin": [-1.65129, 10.25357, -2.67259],
							"size": [0, 0.5, 1],
							"uv": {
								"north": {"uv": [15, 26], "uv_size": [1, 1]},
								"east": {"uv": [14, 26], "uv_size": [2, 1]},
								"south": {"uv": [16, 26], "uv_size": [1, 1]},
								"west": {"uv": [15, 26], "uv_size": [2, 1]},
								"up": {"uv": [16, 25], "uv_size": [-1, 2]},
								"down": {"uv": [16, 27], "uv_size": [-1, -2]}
							}
						}
					]
				},
				{
					"name": "eyelid",
					"parent": "eyes",
					"pivot": [-1.82388, 10.95768, -1.75],
					"cubes": [
						{
							"origin": [-1.75129, 10.61075, -2.7277],
							"size": [0.2, 0.4, 1.275],
							"pivot": [-1.92388, 10.95768, -2],
							"rotation": [-15, 0, 0],
							"uv": {
								"north": {"uv": [15, 27], "uv_size": [1, 1]},
								"east": {"uv": [14, 27], "uv_size": [2, 1]},
								"south": {"uv": [16, 27], "uv_size": [1, 1]},
								"west": {"uv": [15, 26], "uv_size": [2, 1]},
								"up": {"uv": [16, 27], "uv_size": [-1, 2]},
								"down": {"uv": [16, 27], "uv_size": [-1, -2]}
							}
						}
					]
				},
				{
					"name": "iris",
					"parent": "eyes",
					"pivot": [-1.92388, 10.55768, -1.75],
					"cubes": [
						{
							"origin": [-1.70129, 10.25357, -2.07259],
							"size": [0, 0.5, 0.5],
							"uv": {
								"north": {"uv": [17, 26], "uv_size": [1, 1]},
								"east": {"uv": [17, 26], "uv_size": [1, 1]},
								"south": {"uv": [17, 26], "uv_size": [1, 1]},
								"west": {"uv": [17, 26], "uv_size": [1, 1]},
								"up": {"uv": [18, 27], "uv_size": [-1, -1]},
								"down": {"uv": [18, 27], "uv_size": [-1, -1]}
							}
						}
					]
				},
				{
					"name": "helmet",
					"parent": "head",
					"pivot": [-0.42388, 10.70768, -1],
					"cubes": [
						{"origin": [-0.84367, 10.84103, -3.35995], "size": [1.3, 1.3, 1.3], "pivot": [-0.42388, 11.85768, -2.8], "rotation": [-29.7127, -43.65747, 17.40744], "uv": [7, 22]},
						{"origin": [-0.84367, 10.84103, 0.05995], "size": [1.3, 1.3, 1.3], "pivot": [-0.42388, 11.85768, 0.8], "rotation": [29.7127, 43.65747, 17.40744], "uv": [13, 21]}
					]
				},
				{
					"name": "flourish",
					"parent": "helmet",
					"pivot": [0.27612, 12.95768, -1],
					"rotation": [0, 0, 20],
					"cubes": [
						{"origin": [0.12398, 12.04031, -1.5], "size": [1, 1, 1], "uv": [19, 20]}
					]
				},
				{
					"name": "holder",
					"parent": "flourish",
					"pivot": [0.37612, 12.50768, -1],
					"cubes": [
						{"origin": [0.58697, 13.14201, -1.5], "size": [0, 4, 1], "pivot": [0.37612, 13.00768, -1], "rotation": [0, 0, 25], "uv": [14, 2]},
						{"origin": [0.56044, 13.17258, -1.46344], "size": [0, 4, 1], "pivot": [0.37612, 13.00768, -1], "rotation": [12.5, 0, 35], "uv": [2, 8]},
						{"origin": [0.56044, 13.17083, -1.54371], "size": [0, 4, 1], "pivot": [0.37612, 13.00768, -1], "rotation": [-15, 0, 35], "uv": [0, 8]}
					]
				},
				{
					"name": "scarf",
					"parent": "head",
					"pivot": [-0.42388, 9.00768, -1],
					"cubes": [
						{"origin": [-2.26364, 8.40261, -2.83943], "size": [4, 1, 4], "pivot": [-0.42388, 9.00768, -1], "rotation": [2.42095, 45.81429, -10.62774], "uv": [0, 9]}
					]
				},
				{
					"name": "section1",
					"parent": "scarf",
					"pivot": [1.57612, 9.00768, -1],
					"cubes": [
						{"origin": [1.82019, 7.95357, -1], "size": [3, 2, 0], "uv": [14, 19]}
					]
				},
				{
					"name": "section2",
					"parent": "section1",
					"pivot": [4.82612, 8.95768, -1],
					"cubes": [
						{"origin": [4.82019, 7.95357, -1], "size": [3, 2, 0], "uv": [8, 14]}
					]
				},
				{
					"name": "chain",
					"parent": "scarf",
					"pivot": [-1.97388, 8.30768, -1],
					"rotation": [0, 0, 22.5],
					"cubes": [
						{
							"origin": [-1.80693, 6.23587, -1.375],
							"size": [0, 2, 0.75],
							"uv": {
								"north": {"uv": [0, 23], "uv_size": [0, 2]},
								"east": {"uv": [0, 23], "uv_size": [0, 2]},
								"south": {"uv": [0, 23], "uv_size": [0, 2]},
								"west": {"uv": [0, 23], "uv_size": [0, 2]},
								"up": {"uv": [0, 23], "uv_size": [0, 0]},
								"down": {"uv": [0, 23], "uv_size": [0, 0]}
							}
						}
					]
				},
				{
					"name": "chain2",
					"parent": "chain",
					"pivot": [-2.05314, 6.19246, -1],
					"cubes": [
						{
							"origin": [-1.80693, 4.23587, -1.375],
							"size": [0, 2, 0.75],
							"uv": {
								"north": {"uv": [0, 23], "uv_size": [0, 2]},
								"east": {"uv": [0, 23], "uv_size": [0, 2]},
								"south": {"uv": [0, 23], "uv_size": [0, 2]},
								"west": {"uv": [0, 23], "uv_size": [0, 2]},
								"up": {"uv": [0, 23], "uv_size": [0, 0]},
								"down": {"uv": [0, 23], "uv_size": [0, 0]}
							}
						}
					]
				},
				{
					"name": "wingright",
					"parent": "body",
					"pivot": [-0.42388, 8.70768, 1],
					"cubes": [
						{"origin": [-1.87981, 0.65357, 0.45], "size": [3.4, 8, 1], "uv": [0, 14]}
					]
				},
				{
					"name": "wingleft",
					"parent": "body",
					"pivot": [-0.32388, 8.70768, -3],
					"cubes": [
						{"origin": [-2.12388, 0.70768, -3.45], "size": [3.4, 8, 1], "uv": [18, 0]}
					]
				},
				{
					"name": "legs",
					"parent": "torso",
					"pivot": [-0.42388, 3.70768, -1]
				},
				{
					"name": "rightleg",
					"parent": "legs",
					"pivot": [-0.42388, 2.70768, 0.5],
					"rotation": [0, 0, 20],
					"cubes": [
						{"origin": [-0.42824, 0.00778, 0], "size": [0, 2, 1], "uv": [14, 6]},
						{"origin": [-0.92824, 2.00778, 0], "size": [1, 2, 1], "uv": [0, 0]},
						{"origin": [-2.97388, 0.03268, -1], "size": [4, 0, 3], "pivot": [-0.67388, 0.23268, 0.5], "rotation": [0, 0, 2.5], "uv": [14, 22]}
					]
				},
				{
					"name": "rightleg2",
					"parent": "legs",
					"pivot": [-0.42388, 2.70768, -2.5],
					"rotation": [0, 0, 20],
					"cubes": [
						{"origin": [-0.42824, 0.00778, -3], "size": [0, 2, 1], "uv": [14, 6]},
						{"origin": [-0.92824, 2.00778, -3], "size": [1, 2, 1], "uv": [0, 0]},
						{"origin": [-2.97388, 0.03268, -4], "size": [4, 0, 3], "pivot": [-0.67388, 0.23268, -2.5], "rotation": [0, 0, 2.5], "uv": [14, 22]}
					]
				}
			]
		}
	]
}